pyuilder/__init__.py
pyuilder/pyuilder.py
pyuilder-0.0.8.dist-info/LICENSE
pyuilder-0.0.8.dist-info/METADATA
pyuilder-0.0.8.dist-info/WHEEL
pyuilder-0.0.8.dist-info/top_level.txt
pyuilder-0.0.8.dist-info/RECORD
