Metadata-Version: 2.1
Name: pyuilder
Version: 0.0.8
Summary: Provides functionality for implementing the builder pattern in Python.
Author-email: Kevin Jerome <kjerome64@gmail.com>, Connell Boyce <connellboyce17@gmail.com>
Maintainer-email: Kevin Jerome <kjerome64@gmail.com>, Connell Boyce <connellboyce17@gmail.com>
Project-URL: Homepage, https://github.com/kevdog824/pyuilder
Project-URL: Bug Reports, https://github.com/kevdog824/pyuilder/issues
Project-URL: Source, https://github.com/kevdog824/pyuilder
Keywords: builder,builder_pattern,design_patterns
Classifier: Development Status :: 3 - Alpha
Classifier: Intended Audience :: Developers
Classifier: License :: OSI Approved :: MIT License
Classifier: Programming Language :: Python :: 3
Classifier: Programming Language :: Python :: 3.8
Classifier: Programming Language :: Python :: 3.9
Classifier: Programming Language :: Python :: 3.10
Classifier: Programming Language :: Python :: 3.11
Classifier: Programming Language :: Python :: 3.12
Classifier: Programming Language :: Python :: 3 :: Only
Requires-Python: >=3.8
License-File: LICENSE
Requires-Dist: typing-extensions ==4.11.0
Provides-Extra: ci
Requires-Dist: pyuilder[dev] ; extra == 'ci'
Requires-Dist: pyuilder[test] ; extra == 'ci'
Requires-Dist: pyuilder[publish] ; extra == 'ci'
Provides-Extra: dev
Requires-Dist: mypy ==1.10.0 ; extra == 'dev'
Requires-Dist: ruff ==0.4.3 ; extra == 'dev'
Provides-Extra: publish
Requires-Dist: build ==1.2.1 ; extra == 'publish'
Requires-Dist: twine ==5.0.0 ; extra == 'publish'
Provides-Extra: test
Requires-Dist: pytest ==8.2.0 ; extra == 'test'
Requires-Dist: pytest-cov ==5.0.0 ; extra == 'test'
